pygsim/__init__.py
pygsim/core.py
pygsim/util.py
pygsim/version.py
pygsim/drawing/__init__.py
pygsim/drawing/color.py
pygsim/drawing/container.py
pygsim/drawing/drawable.py
pygsim/drawing/shape.py
pygsim/drawing/text.py
pygsim-0.1.0.dist-info/LICENSE
pygsim-0.1.0.dist-info/METADATA
pygsim-0.1.0.dist-info/WHEEL
pygsim-0.1.0.dist-info/top_level.txt
pygsim-0.1.0.dist-info/RECORD
