Metadata-Version: 2.1
Name: pygsim
Version: 0.1.0
Summary: Graphical interface for SimPY with PyGame
Home-page: https://github.com/honzad/pygsim
Author: Jan Ďurďák
Author-email: Jan Ďurďák <jandurdak@seznam.cz>
License: The MIT License (MIT)
Project-URL: Homepage, https://github.com/honzad/pygsim
Project-URL: Documentation, https://github.com/honzad/pygsim/wiki
Project-URL: Source, https://github.com/honzad/pygsim
Project-URL: Tracker, https://github.com/honzad/pygsim/issues
Keywords: python,simulation,visualizer
Classifier: Development Status :: 2 - Pre-Alpha
Classifier: Intended Audience :: Developers
Classifier: Intended Audience :: Science/Research
Classifier: Intended Audience :: Education
Classifier: Topic :: Scientific/Engineering
Classifier: Programming Language :: Python :: 3
Classifier: Operating System :: Unix
Classifier: Operating System :: MacOS :: MacOS X
Classifier: Operating System :: Microsoft :: Windows
Requires-Python: >=3.6
License-File: LICENSE
Requires-Dist: simpy
Requires-Dist: pygame
Requires-Dist: numpy
Provides-Extra: dev
Requires-Dist: flake8 ; extra == 'dev'
Requires-Dist: black ; extra == 'dev'
Requires-Dist: bumpver ; extra == 'dev'
